showip/__init__.py
showip/cli.py
showip/showip.py
showip-1.1.5.dist-info/LICENSE
showip-1.1.5.dist-info/METADATA
showip-1.1.5.dist-info/WHEEL
showip-1.1.5.dist-info/entry_points.txt
showip-1.1.5.dist-info/top_level.txt
showip-1.1.5.dist-info/RECORD
