Metadata-Version: 2.1
Name: showip
Version: 1.1.5
Summary: Get information about your IP or any other IP
Home-page: https://github.com/varvaruk-v/showip
Author: Viktor Varvaruk
Author-email: 
License: MIT
Requires-Python: >=3.7.0
License-File: LICENSE
Requires-Dist: requests
